pyAttention/__init__.py
pyAttention/collection.py
pyAttention/exception.py
pyAttention/media.py
pyAttention/parser.py
pyAttention/source.py
pyAttention/util.py
pyattention-0.1.3.dist-info/METADATA
pyattention-0.1.3.dist-info/WHEEL
pyattention-0.1.3.dist-info/RECORD
