Metadata-Version: 2.1
Name: pyAttention
Version: 0.1.3
Summary: A library to monitor information sources
Home-page: https://github.com/dhrone/pyAttention
License: MIT
Keywords: pyAttention,data,database,rss,sql,socketio,websocket,volumio,mpd,light,weight,message,broker
Author: dhrone
Author-email: dhrone@dhrone.xyz
Requires-Python: >=3.9,<4.0
Classifier: Development Status :: 3 - Alpha
Classifier: Environment :: Console
Classifier: Intended Audience :: Developers
Classifier: License :: OSI Approved :: MIT License
Classifier: Operating System :: OS Independent
Classifier: Programming Language :: Python :: 3
Classifier: Programming Language :: Python :: 3.9
Classifier: Programming Language :: Python :: 3.10
Classifier: Programming Language :: Python :: 3.11
Classifier: Programming Language :: Python :: 3.12
Classifier: Topic :: Software Development :: Libraries :: Python Modules
Requires-Dist: greenlet (>=3.0.3,<4.0.0)
Project-URL: Repository, https://github.com/dhrone/pyAttention
